toypackage/__init__.py
toypackage/toypackage.py
toypackage-0.1.0.dist-info/LICENSE
toypackage-0.1.0.dist-info/WHEEL
toypackage-0.1.0.dist-info/METADATA
toypackage-0.1.0.dist-info/RECORD
